LICENSE
MANIFEST.in
README.rst
setup.py
cmsplugin_polls/__init__.py
cmsplugin_polls/admin.py
cmsplugin_polls/cms_plugins.py
cmsplugin_polls/models.py
cmsplugin_polls/urls.py
cmsplugin_polls/views.py
cmsplugin_polls.egg-info/PKG-INFO
cmsplugin_polls.egg-info/SOURCES.txt
cmsplugin_polls.egg-info/dependency_links.txt
cmsplugin_polls.egg-info/not-zip-safe
cmsplugin_polls.egg-info/requires.txt
cmsplugin_polls.egg-info/top_level.txt
cmsplugin_polls/locale/en/LC_MESSAGES/django.mo
cmsplugin_polls/locale/en/LC_MESSAGES/django.po
cmsplugin_polls/locale/ru/LC_MESSAGES/django.mo
cmsplugin_polls/locale/ru/LC_MESSAGES/django.po
cmsplugin_polls/migrations/0001_initial.py
cmsplugin_polls/migrations/__init__.py
cmsplugin_polls/south_migrations/0001_initial.py
cmsplugin_polls/south_migrations/__init__.py
cmsplugin_polls/templates/cms/plugins/poll.html
cmsplugin_polls/templates/cms/plugins/poll_form.html
cmsplugin_polls/templates/cms/plugins/poll_results.html
cmsplugin_polls/templatetags/__init__.py
cmsplugin_polls/templatetags/poll_tags.py